ros/__init__.py
ros/_base.py
ros/_literals.py
ros/_utils.py
ros/error.py
ros/inteface/__init__.py
ros/inteface/bridge/__init__.py
ros/inteface/bridge/bridge.py
ros/inteface/bridge/msti.py
ros/inteface/bridge/port.py
ros/inteface/bridge/vlan.py
ros/inteface/eoip.py
ros/inteface/ethernet.py
ros/inteface/interface.py
ros/inteface/list/__init__.py
ros/inteface/list/list.py
ros/inteface/list/member.py
ros/inteface/veth.py
ros/inteface/vlan.py
ros/inteface/vrrp.py
ros/inteface/wireguard/__init__.py
ros/inteface/wireguard/wireguard.py
ros/ip/__init__.py
ros/ip/address.py
ros/ip/arp.py
ros/ip/cloud.py
ros/ip/dhcp_client.py
ros/ip/dhcp_relay.py
ros/ip/dhcp_server/__init__.py
ros/ip/dhcp_server/_literals.py
ros/ip/dhcp_server/dhcp_server.py
ros/ip/dhcp_server/lease.py
ros/ip/dhcp_server/network.py
ros/ip/dns/__init__.py
ros/ip/dns/_literals.py
ros/ip/dns/cache.py
ros/ip/dns/static.py
ros/ip/firewall/__init__.py
ros/ip/firewall/_literals.py
ros/ip/firewall/address_list.py
ros/ip/firewall/connection.py
ros/ip/firewall/filter.py
ros/ip/firewall/mangle.py
ros/ip/firewall/nat.py
ros/ip/hotspot/__init__.py
ros/ip/hotspot/active.py
ros/ip/hotspot/cookie.py
ros/ip/hotspot/host.py
ros/ip/hotspot/hotspot.py
ros/ip/hotspot/ip_binding.py
ros/ip/hotspot/profile.py
ros/ip/hotspot/service_port.py
ros/ip/hotspot/user/__init__.py
ros/ip/hotspot/user/profile.py
ros/ip/hotspot/walled_garden/__init__.py
ros/ip/hotspot/walled_garden/ip.py
ros/ip/kid_control/__init__.py
ros/ip/kid_control/device.py
ros/ip/kid_control/kid.py
ros/ip/neighbor.py
ros/ip/pool.py
ros/ip/route.py
ros/ip/service.py
ros/ip/setting.py
ros/ip/vrf.py
ros/log.py
ros/mpls/__init__.py
ros/mpls/forwarding_table.py
ros/mpls/interface.py
ros/mpls/ldp/__init__.py
ros/mpls/ldp/accept_filter.py
ros/mpls/ldp/advertise_filter.py
ros/mpls/ldp/instance.py
ros/mpls/ldp/interface.py
ros/mpls/ldp/local_mapping.py
ros/mpls/ldp/neighbor.py
ros/mpls/ldp/remote_mapping.py
ros/mpls/settings.py
ros/ppp/__init__.py
ros/ppp/_literals.py
rosrestpy-0.12.2.dist-info/LICENSE
rosrestpy-0.12.2.dist-info/METADATA
rosrestpy-0.12.2.dist-info/WHEEL
rosrestpy-0.12.2.dist-info/RECORD
