Metadata-Version: 2.1
Name: rosrestpy
Version: 0.12.2
Summary: RouterOS v7 REST API python module
Home-page: https://github.com/hexatester/rosrestpy
License: GPL-3.0-only
Author: hexatester
Author-email: hexatester@protonmail.com
Requires-Python: >=3.8,<4.0
Classifier: Development Status :: 4 - Beta
Classifier: Intended Audience :: Developers
Classifier: License :: OSI Approved :: GNU General Public License v3 (GPLv3)
Classifier: Operating System :: OS Independent
Classifier: Programming Language :: Python
Classifier: Programming Language :: Python :: 3
Classifier: Programming Language :: Python :: 3.8
Classifier: Programming Language :: Python :: 3.9
Classifier: Programming Language :: Python :: 3.10
Classifier: Programming Language :: Python :: 3.11
Classifier: Programming Language :: Python :: 3.12
Classifier: Topic :: Software Development :: Libraries :: Python Modules
Classifier: Topic :: System :: Networking
Provides-Extra: ujson
Requires-Dist: attrs (>=21.0.0,<=23.0.0)
Requires-Dist: cattrs (>=21.0.0,<=23.0.0)
Requires-Dist: requests (>=2.31.0)
Requires-Dist: ujson (>=5.5.0,<6.0.0) ; extra == "ujson"
Project-URL: Repository, https://github.com/hexatester/rosrestpy
